mkdocs_licenseinfo/__init__.py
mkdocs_licenseinfo/_version.py
mkdocs_licenseinfo/extension.py
mkdocs_licenseinfo/get_licenses.py
mkdocs_licenseinfo/plugin.py
mkdocs_licenseinfo/render_markdown.py
mkdocs_licenseinfo-0.1.0.dist-info/LICENSE
mkdocs_licenseinfo-0.1.0.dist-info/METADATA
mkdocs_licenseinfo-0.1.0.dist-info/WHEEL
mkdocs_licenseinfo-0.1.0.dist-info/entry_points.txt
mkdocs_licenseinfo-0.1.0.dist-info/top_level.txt
mkdocs_licenseinfo-0.1.0.dist-info/RECORD
