Metadata-Version: 2.1
Name: mkdocs_licenseinfo
Version: 0.1.0
Summary: mkdocs extension to visualise package dependencies license information
Author-email: David J Pugh <djpugh@gmail.com>
Maintainer-email: David J Pugh <djpugh@gmail.com>
Project-URL: repository, https://github.com/djpugh/mkdocs_licenseinfo
Keywords: mkdocs,mkdocs-plugin,license,licenseinfo,documentation,sbom
Classifier: Environment :: Console
Classifier: Topic :: Software Development :: Libraries :: Python Modules
Classifier: Programming Language :: Python :: 3
Classifier: Programming Language :: Python :: 3.8
Classifier: Programming Language :: Python :: 3.9
Classifier: Programming Language :: Python :: 3.10
Classifier: Programming Language :: Python :: 3.11
Classifier: Programming Language :: Python :: 3.12
Classifier: Intended Audience :: Developers
Classifier: License :: OSI Approved :: MIT License
Classifier: Operating System :: Microsoft :: Windows
Classifier: Operating System :: POSIX :: Linux
Classifier: Operating System :: MacOS :: MacOS X
Classifier: Natural Language :: English
Requires-Python: >3.7
License-File: LICENSE
Requires-Dist: licensecheck
Requires-Dist: mkdocs >=1.4
Requires-Dist: importlib-metadata >=4.6 ; python_version < "3.10"
Requires-Dist: backports.entry-points-selectable ; python_version < "3.10"
Requires-Dist: importlib-metadata ; python_version < "3.11"
Requires-Dist: typing-extensions ; python_version < "3.12"
Provides-Extra: dev
Requires-Dist: setuptools-scm[toml] ; extra == 'dev'
Requires-Dist: nox ; extra == 'dev'
Provides-Extra: dev-build
Requires-Dist: build ; extra == 'dev-build'
Provides-Extra: dev-docs
Requires-Dist: mkdocs ; extra == 'dev-docs'
Requires-Dist: mkdocstrings[python] ; extra == 'dev-docs'
Requires-Dist: mkdocs-git-revision-date-localized-plugin ; extra == 'dev-docs'
Requires-Dist: mkdocs-material ; extra == 'dev-docs'
Requires-Dist: mkdocs-git-authors-plugin ; extra == 'dev-docs'
Requires-Dist: mkdocs-coverage ; extra == 'dev-docs'
Requires-Dist: mkdocs-include-markdown-plugin ; extra == 'dev-docs'
Requires-Dist: mkdocs-github-changelog ; extra == 'dev-docs'
Requires-Dist: mike ; extra == 'dev-docs'
Provides-Extra: dev-lint
Requires-Dist: flake8 >=5.0.4 ; extra == 'dev-lint'
Requires-Dist: flake8-import-order >=0.18.2 ; extra == 'dev-lint'
Requires-Dist: flake8-eradicate >=1.4.0 ; extra == 'dev-lint'
Requires-Dist: flake8-docstrings >=0.2.7 ; extra == 'dev-lint'
Requires-Dist: flake8-pyproject >=1.2.3 ; extra == 'dev-lint'
Requires-Dist: flake8-bugbear >=22.0.0 ; extra == 'dev-lint'
Requires-Dist: flake8-comprehensions >=3.12.0 ; extra == 'dev-lint'
Requires-Dist: flake8-unused-arguments >=0.0.13 ; extra == 'dev-lint'
Requires-Dist: flake8-noqa >=1.3.1 ; extra == 'dev-lint'
Provides-Extra: dev-security
Requires-Dist: pipenv ; extra == 'dev-security'
Requires-Dist: bandit ; extra == 'dev-security'
Provides-Extra: dev-test
Requires-Dist: pytest >=7.3.1 ; extra == 'dev-test'
Requires-Dist: pytest-cov >=4 ; extra == 'dev-test'
Requires-Dist: pytest-subtests ; extra == 'dev-test'
Requires-Dist: nskit ; extra == 'dev-test'
Requires-Dist: mkdocs-material ; extra == 'dev-test'
Provides-Extra: dev-types
Requires-Dist: mypy ; extra == 'dev-types'
Requires-Dist: types-colorama ; extra == 'dev-types'
Requires-Dist: types-setuptools ; extra == 'dev-types'
Requires-Dist: importlib-metadata ; (python_version < "3.8") and extra == 'dev'
